calc_app_ab/__init__.py
calc_app_ab/add.py
calc_app_ab/subtract.py
extras/__init__.py
extras/divide.py
extras/multiply.py
calc_app_ab-0.0.1.dist-info/METADATA
calc_app_ab-0.0.1.dist-info/WHEEL
calc_app_ab-0.0.1.dist-info/top_level.txt
calc_app_ab-0.0.1.dist-info/RECORD
